wort/__init__.py
wort/app.py
wort/tasks.py
wort-0.0.1.dist-info/LICENSE
wort-0.0.1.dist-info/WHEEL
wort-0.0.1.dist-info/METADATA
wort-0.0.1.dist-info/RECORD
