Metadata-Version: 1.2
Name: wort
Version: 0.0.1
Summary: A web service for sourmash operations.
Home-page: http://luizirber.org
License: UNKNOWN
Author: Luiz Irber
Author-email: wort@luizirber.org
Classifier: License :: OSI Approved :: MIT License
